{
	"class" : {
		 },
	"instance" : {
		"bootstrapRoot" : "CamilloBruni 10/18/2013 16:23",
		"bootstrapRoot:" : "CamilloBruni 10/18/2013 10:31",
		"exportMergeRecord:" : "CamilloBruni 10/18/2013 18:46",
		"htmlBeginning:" : "CamilloBruni 10/18/2013 16:03",
		"htmlEnding:" : "CamilloBruni 10/18/2013 11:18",
		"initialize" : "CamilloBruni 10/18/2013 15:16",
		"newStream" : "CamilloBruni 10/22/2013 22:19",
		"publishChangeNotFound:" : "CamilloBruni 10/18/2013 18:04",
		"publishError:" : "CamilloBruni 10/18/2013 15:28",
		"publishFailures:" : "CamilloBruni 10/18/2013 11:23",
		"publishLintRule:" : "CamilloBruni 10/18/2013 18:50",
		"publishList:kind:do:" : "CamilloBruni 10/18/2013 15:17",
		"publishMergeConflict:" : "CamilloBruni 10/18/2013 18:55",
		"publishMergeConflicts:class:" : "CamilloBruni 10/18/2013 18:56",
		"publishMessages:" : "CamilloBruni 10/18/2013 11:23",
		"publishResultGroupWithTitle:count:with:" : "CamilloBruni 10/18/2013 18:06",
		"publishResultGroupWithTitle:with:" : "CamilloBruni 10/18/2013 15:24",
		"publishResultList:title:" : "CamilloBruni 10/18/2013 18:08",
		"publishSuccess:" : "CamilloBruni 10/18/2013 12:12",
		"publishSummary:" : "CamilloBruni 10/18/2013 18:04",
		"publishSummaryLabel:count:type:" : "CamilloBruni 10/18/2013 18:07",
		"publishValidationResult:" : "CamilloBruni 10/22/2013 22:18",
		"publishWarnings:" : "CamilloBruni 10/18/2013 11:23",
		"stream:" : "CamilloBruni 10/18/2013 10:30",
		"writer" : "CamilloBruni 10/18/2013 10:30" } }
