{
	"class" : {
		"example" : "CamilloBruni 9/22/2011 19:47",
		"issue:" : "BenjaminVanRyseghem 9/21/2011 14:37" },
	"instance" : {
		"addError:" : "CamilloBruni 9/22/2011 21:16",
		"addError:forFile:" : "CamilloBruni 9/22/2011 21:20",
		"buildErrorReportOn:" : "CamilloBruni 9/25/2011 04:56",
		"buildGreenReport" : "CamilloBruni 9/23/2011 15:38",
		"buildGreenReportOn:" : "CamilloBruni 9/25/2011 05:56",
		"buildGreenTitleOn:" : "MonkeyGalactikalIntegrator 9/25/2011 06:30",
		"buildRedReport" : "CamilloBruni 9/23/2011 15:38",
		"buildRedReportOn:" : "CamilloBruni 9/25/2011 05:06",
		"buildSetupDescriptionOn:" : "CamilloBruni 9/25/2011 05:22",
		"buildTestsReportOn:" : "CamilloBruni 9/22/2011 18:50",
		"coreTests" : "CamilloBruni 9/25/2011 15:06",
		"dirtyPackagesTests" : "BenjaminVanRyseghem 9/26/2011 19:01",
		"errorNoLoadableSources" : "BenjaminVanRyseghem 9/25/2011 17:07",
		"extraTests" : "BenjaminVanRyseghem 9/22/2011 16:13",
		"impactedPackagesTests" : "BenjaminVanRyseghem 9/26/2011 18:27",
		"initialize" : "CamilloBruni 9/23/2011 15:35",
		"isAllGreen" : "CamilloBruni 9/23/2011 15:38",
		"isCog" : "CamilloBruni 9/23/2011 16:43",
		"isGreen" : "CamilloBruni 9/23/2011 16:19",
		"issue" : "BenjaminVanRyseghem 9/21/2011 17:10",
		"issue:" : "CamilloBruni 9/22/2011 13:53",
		"load" : "BenjaminVanRyseghem 9/25/2011 17:41",
		"loadAndTest" : "BenjaminVanRyseghem 9/25/2011 17:51",
		"loadAndTestChangeSet" : "CamilloBruni 9/23/2011 15:27",
		"loadAndTestSlice" : "CamilloBruni 9/25/2011 05:04",
		"loadChangeSet" : "BenjaminVanRyseghem 9/25/2011 19:44",
		"loadSlice" : "BenjaminVanRyseghem 9/25/2011 19:45",
		"notifyTracker" : "CamilloBruni 9/23/2011 15:39",
		"preRunTests" : "CamilloBruni 9/22/2011 09:41",
		"removeCriticalTestsFrom:" : "CamilloBruni 9/25/2011 03:54",
		"removeFalseErrors" : "CamilloBruni 9/22/2011 19:29",
		"reset" : "CamilloBruni 9/23/2011 15:36",
		"retrieveTestClasses" : "CamilloBruni 9/23/2011 16:21",
		"runAllTests" : "CamilloBruni 9/22/2011 14:22",
		"runTests" : "CamilloBruni 9/25/2011 03:54",
		"slice" : "BenjaminVanRyseghem 9/25/2011 02:36",
		"testChangeImpact:" : "MonkeyGalactikalIntegrator 9/25/2011 21:28",
		"testClassesToBeChecked" : "BenjaminVanRyseghem 9/26/2011 18:38",
		"testResult" : "BenjaminVanRyseghem 9/21/2011 17:10",
		"testResult:" : "BenjaminVanRyseghem 9/21/2011 17:10" } }
