{
	"class" : {
		"spec" : "EstebanLorenzano 9/18/2014 17:14" },
	"instance" : {
		"config:" : "EstebanLorenzano 9/18/2014 17:16",
		"externalBrowserLabel" : "EstebanLorenzano 9/18/2014 17:14",
		"externalBrowserLabel:" : "EstebanLorenzano 9/18/2014 17:14",
		"externalBrowserText" : "EstebanLorenzano 9/18/2014 17:14",
		"externalBrowserText:" : "EstebanLorenzano 9/18/2014 17:14",
		"initialExtent" : "EstebanLorenzano 9/18/2014 17:15",
		"initializeWidgets" : "EstebanLorenzano 9/18/2014 17:19",
		"newConfig" : "EstebanLorenzano 9/18/2014 17:16",
		"passwordLabel" : "EstebanLorenzano 9/17/2014 15:46",
		"passwordLabel:" : "EstebanLorenzano 9/17/2014 15:46",
		"passwordText" : "EstebanLorenzano 9/17/2014 15:46",
		"passwordText:" : "EstebanLorenzano 9/17/2014 15:46",
		"title" : "EstebanLorenzano 9/17/2014 15:51",
		"usernameLabel" : "EstebanLorenzano 9/17/2014 15:46",
		"usernameLabel:" : "EstebanLorenzano 9/17/2014 15:46",
		"usernameText" : "EstebanLorenzano 9/17/2014 15:46",
		"usernameText:" : "EstebanLorenzano 9/17/2014 15:46",
		"versionLabel" : "EstebanLorenzano 9/17/2014 15:46",
		"versionLabel:" : "EstebanLorenzano 9/17/2014 15:46",
		"versionText" : "EstebanLorenzano 9/17/2014 15:46",
		"versionText:" : "EstebanLorenzano 9/17/2014 15:46" } }
