{
	"class" : {
		"source:" : "CamilloBruni 10/16/2013 15:47" },
	"instance" : {
		"asCIChange" : "CI Validation User 5/8/2013 13:39",
		"assertLoadable" : "CamilloBruni 4/14/2013 22:43",
		"basicLoad" : "CamilloBruni 4/14/2013 22:44",
		"changeValidationRule" : "ErwanDouaille 5/27/2013 18:10",
		"id" : "ErwanDouaille 4/11/2013 16:24",
		"isLoadable" : "CamilloBruni 4/14/2013 22:25",
		"load" : "CamilloBruni 5/14/2013 14:29",
		"manager" : "CamilloBruni 4/14/2013 21:42",
		"name" : "CamilloBruni 4/14/2013 23:25",
		"printOn:" : "CI Validation User 5/28/2013 08:38",
		"publicUrl" : "BenjaminVanRyseghem 3/22/2013 18:36",
		"source" : "CamilloBruni 4/10/2013 16:21",
		"source:" : "CamilloBruni 4/10/2013 16:21",
		"url" : "CamilloBruni 10/15/2013 22:15" } }
